[{"date": "2011-10-09T00:00:00.000000Z", "id": "a68fd405-5548-5538-8fbb-a5046c8a978f", "name": "Columbus Blue Jackets @ Minnesota Wild"}, {"date": "2011-10-10T17:00:00.000000Z", "id": "e1b734f0-4f45-5375-92ec-38a23ddd9a30", "name": "Minnesota Wild @ New York Islanders"}, {"date": "2011-10-11T23:30:00.000000Z", "id": "b5368fbc-6a99-5eed-925b-6ae91260743e", "name": "Minnesota Wild @ Ottawa Senators"}, {"date": "2011-10-14T00:00:00.000000Z", "id": "90dae769-edd0-542f-93cf-aa8a6a6b9566", "name": "Edmonton Oilers @ Minnesota Wild"}, {"date": "2011-10-16T00:00:00.000000Z", "id": "244c8294-0708-57d0-aef0-a287ad7f8fe2", "name": "Detroit Red Wings @ Minnesota Wild"}, {"date": "2011-10-18T23:30:00.000000Z", "id": "facb3982-1a9b-5a95-a329-a14f3263af7b", "name": "Pittsburgh Penguins @ Minnesota Wild"}, {"date": "2011-10-21T01:30:00.000000Z", "id": "f341916f-4728-5cf7-8809-e145e0f7f2ce", "name": "Minnesota Wild @ Edmonton Oilers"}, {"date": "2011-10-22T20:00:00.000000Z", "id": "c9d25a5b-fec5-5067-8220-5295ee04bbf8", "name": "Minnesota Wild @ Vancouver Canucks"}, {"date": "2011-10-28T00:00:00.000000Z", "id": "ff034f02-4138-5925-9edb-1ddd4137ad3b", "name": "Anaheim Ducks @ Minnesota Wild"}, {"date": "2011-10-30T00:00:00.000000Z", "id": "0061d160-5678-598a-b42c-ccb7d55c5842", "name": "Detroit Red Wings @ Minnesota Wild"}, {"date": "2011-11-01T23:30:00.000000Z", "id": "2ff111b3-ad52-57cd-8b69-c3f2ef99d09a", "name": "Minnesota Wild @ Detroit Red Wings"}, {"date": "2011-11-04T00:00:00.000000Z", "id": "92becadb-bb77-5f72-a61e-3ead1f457167", "name": "Vancouver Canucks @ Minnesota Wild"}, {"date": "2011-11-06T00:00:00.000000Z", "id": "513c1668-d86a-56ce-9b1f-492476e275d5", "name": "St Louis Blues @ Minnesota Wild"}, {"date": "2011-11-09T02:30:00.000000Z", "id": "236fb563-2ed4-50db-ad7d-bad7ed26f705", "name": "Minnesota Wild @ Calgary Flames"}, {"date": "2011-11-11T03:30:00.000000Z", "id": "dd43c749-2910-5d84-9ea9-4b189fb24c7d", "name": "Minnesota Wild @ San Jose Sharks"}, {"date": "2011-11-13T03:30:00.000000Z", "id": "fb80865e-4bcb-59fd-b20e-bf6837a3d510", "name": "Minnesota Wild @ Los Angeles Kings"}, {"date": "2011-11-14T01:00:00.000000Z", "id": "82bbacbc-3ae5-5dc0-a011-4880287d75cf", "name": "Minnesota Wild @ Anaheim Ducks"}, {"date": "2011-11-16T00:00:00.000000Z", "id": "76e9cec1-043a-5f26-9a7c-f20af3825403", "name": "Minnesota Wild @ Columbus Blue Jackets"}, {"date": "2011-11-18T01:00:00.000000Z", "id": "51431d3c-a687-59af-b705-39e21caadb77", "name": "Colorado Avalanche @ Minnesota Wild"}, {"date": "2011-11-20T01:00:00.000000Z", "id": "7a58b20a-4aef-5198-8aba-4abb722ba687", "name": "St Louis Blues @ Minnesota Wild"}, {"date": "2011-11-24T01:00:00.000000Z", "id": "26b6f158-1711-52b3-aeca-8b51ffb33460", "name": "Nashville Predators @ Minnesota Wild"}, {"date": "2011-11-25T21:00:00.000000Z", "id": "838a3ffe-76b1-5204-a601-5952480fc769", "name": "Edmonton Oilers @ Minnesota Wild"}, {"date": "2011-11-27T23:00:00.000000Z", "id": "7bbd459c-229f-5347-92ee-46bdffac8adf", "name": "Calgary Flames @ Minnesota Wild"}, {"date": "2011-11-29T00:30:00.000000Z", "id": "b447aed0-454b-5b1b-9ca0-7fc8424de7be", "name": "Tampa Bay Lightning @ Minnesota Wild"}, {"date": "2011-12-01T02:30:00.000000Z", "id": "84d8dfad-8f7f-544d-929d-9e1cd9d77c9c", "name": "Minnesota Wild @ Edmonton Oilers"}, {"date": "2011-12-03T01:00:00.000000Z", "id": "77b5e2fa-73f6-53f5-998c-90a9af4362b8", "name": "New Jersey Devils @ Minnesota Wild"}, {"date": "2011-12-05T01:00:00.000000Z", "id": "de38d018-dee0-5342-a0c4-f3dcfa644111", "name": "Minnesota Wild @ Anaheim Ducks"}, {"date": "2011-12-07T03:30:00.000000Z", "id": "8bbd1169-218a-55b1-bac7-c101d307d65c", "name": "Minnesota Wild @ San Jose Sharks"}, {"date": "2011-12-09T03:30:00.000000Z", "id": "46aaad22-5ff0-5299-a44d-25e72bbaa4ee", "name": "Minnesota Wild @ Los Angeles Kings"}, {"date": "2011-12-11T01:00:00.000000Z", "id": "29d2824d-2968-5fb9-8386-485362f03a21", "name": "Minnesota Wild @ Phoenix Coyotes"}, {"date": "2011-12-14T01:30:00.000000Z", "id": "38d23159-7ccb-5637-a3b0-9b040589f684", "name": "Minnesota Wild @ Winnipeg Jets"}, {"date": "2011-12-15T00:30:00.000000Z", "id": "56684da3-ad1d-57a3-8281-188357100b61", "name": "Chicago Blackhawks @ Minnesota Wild"}, {"date": "2011-12-18T01:00:00.000000Z", "id": "6b6a1a23-8202-5bb2-97b0-90bf9b4e5f08", "name": "New York Islanders @ Minnesota Wild"}, {"date": "2011-12-20T03:00:00.000000Z", "id": "542fb1a9-a39a-5908-910c-1990cafefbbc", "name": "Minnesota Wild @ Vancouver Canucks"}, {"date": "2011-12-21T02:00:00.000000Z", "id": "75afe77c-3bf2-511c-8776-e45264f8858f", "name": "Minnesota Wild @ Calgary Flames"}, {"date": "2011-12-23T02:30:00.000000Z", "id": "1140e0ed-e98b-5b51-a365-bd9dcf646f64", "name": "Minnesota Wild @ Edmonton Oilers"}, {"date": "2011-12-26T23:00:00.000000Z", "id": "5147220f-b8a6-595c-aa66-4f282ad41d48", "name": "Colorado Avalanche @ Minnesota Wild"}, {"date": "2011-12-29T01:00:00.000000Z", "id": "b723301d-d932-5893-acd5-28643600499c", "name": "Minnesota Wild @ Nashville Predators"}, {"date": "2011-12-30T01:00:00.000000Z", "id": "dd990f4b-5846-5a4d-8cb6-90feb7217adb", "name": "Edmonton Oilers @ Minnesota Wild"}, {"date": "2011-12-31T23:00:00.000000Z", "id": "594a9e7f-eb83-5e33-ac24-f2c569c90f8e", "name": "Phoenix Coyotes @ Minnesota Wild"}, {"date": "2012-01-05T03:00:00.000000Z", "id": "0d53b9bb-d7a8-53aa-8ad0-c54368e64b15", "name": "Minnesota Wild @ Vancouver Canucks"}, {"date": "2012-01-08T03:00:00.000000Z", "id": "61028ea3-b19d-5e29-aacf-178b5a8f9f7c", "name": "Minnesota Wild @ Calgary Flames"}, {"date": "2012-01-11T00:30:00.000000Z", "id": "5b1be5b0-a636-5e1a-bde6-e643f4584db2", "name": "San Jose Sharks @ Minnesota Wild"}, {"date": "2012-01-13T01:30:00.000000Z", "id": "5f35915b-3f1b-5439-b50d-a0d57b4d3f60", "name": "Minnesota Wild @ Chicago Blackhawks"}, {"date": "2012-01-15T01:00:00.000000Z", "id": "68344bea-6bdc-5527-8bd0-f7cb0c156a22", "name": "Minnesota Wild @ St Louis Blues"}, {"date": "2012-01-18T00:00:00.000000Z", "id": "7dec80f0-7eb1-5514-95dc-65a8cf4ed2cd", "name": "Minnesota Wild @ Philadelphia Flyers"}, {"date": "2012-01-20T00:00:00.000000Z", "id": "9c650dcf-41e6-57be-90a8-b4935af28712", "name": "Minnesota Wild @ Toronto Maple Leafs"}, {"date": "2012-01-22T02:00:00.000000Z", "id": "924c5348-e10f-5f2f-a003-914ee007cdd8", "name": "Dallas Stars @ Minnesota Wild"}, {"date": "2012-01-25T02:00:00.000000Z", "id": "6e6dddc9-c09a-55d6-8aec-df75264947ba", "name": "Minnesota Wild @ Colorado Avalanche"}, {"date": "2012-02-01T01:00:00.000000Z", "id": "13b3dfdb-e970-59e9-b103-485d07a6d649", "name": "Nashville Predators @ Minnesota Wild"}, {"date": "2012-02-03T02:00:00.000000Z", "id": "060ea872-9c8e-55d3-8d57-8cbc376b83a8", "name": "Minnesota Wild @ Colorado Avalanche"}, {"date": "2012-02-05T01:00:00.000000Z", "id": "72ea6094-6d9a-5f98-b667-268f671566f1", "name": "Minnesota Wild @ Dallas Stars"}, {"date": "2012-02-08T00:00:00.000000Z", "id": "c7ac8be2-f851-5faa-98f3-0ad8fc745f0d", "name": "Minnesota Wild @ Columbus Blue Jackets"}, {"date": "2012-02-10T01:00:00.000000Z", "id": "81eae1d0-20c2-5027-b4da-96e48c0effed", "name": "Vancouver Canucks @ Minnesota Wild"}, {"date": "2012-02-12T01:00:00.000000Z", "id": "9532059f-0643-5d4f-ae83-b58480d46d46", "name": "Columbus Blue Jackets @ Minnesota Wild"}, {"date": "2012-02-15T00:30:00.000000Z", "id": "b55b9ec0-f338-505d-981e-c93e6f5b337b", "name": "Anaheim Ducks @ Minnesota Wild"}, {"date": "2012-02-17T01:00:00.000000Z", "id": "29212ee5-1152-5e6b-8fb9-3b44a16b35ad", "name": "Winnipeg Jets @ Minnesota Wild"}, {"date": "2012-02-18T19:00:00.000000Z", "id": "eec70560-b0b1-5d1a-95d6-46778c258678", "name": "Minnesota Wild @ St Louis Blues"}, {"date": "2012-02-19T20:00:00.000000Z", "id": "5b3dc26f-df41-5a92-bbae-56b0e7e09f62", "name": "Boston Bruins @ Minnesota Wild"}, {"date": "2012-02-24T00:30:00.000000Z", "id": "98a281dc-13ea-54c8-a883-d1adc2053b41", "name": "Minnesota Wild @ Florida Panthers"}, {"date": "2012-02-25T01:30:00.000000Z", "id": "8fa4b4d8-3bb4-5c6f-bf31-6f36be9316ec", "name": "Minnesota Wild @ Dallas Stars"}, {"date": "2012-02-26T23:00:00.000000Z", "id": "f1bf403e-87ff-5824-986a-25bb70462d92", "name": "San Jose Sharks @ Minnesota Wild"}, {"date": "2012-02-29T00:30:00.000000Z", "id": "7665f866-f559-5b24-a637-35e1f31e0738", "name": "Los Angeles Kings @ Minnesota Wild"}, {"date": "2012-03-02T00:00:00.000000Z", "id": "460d16f1-5945-5e09-acb6-54a874aa7937", "name": "Minnesota Wild @ Montreal Canadiens"}, {"date": "2012-03-03T00:30:00.000000Z", "id": "66ce0741-2328-53f3-b1b7-42c65ec6c646", "name": "Minnesota Wild @ Detroit Red Wings"}, {"date": "2012-03-05T00:00:00.000000Z", "id": "5418cfa8-33cf-5332-8be3-d10c174469b2", "name": "Colorado Avalanche @ Minnesota Wild"}, {"date": "2012-03-07T02:00:00.000000Z", "id": "b23377ba-662e-57e0-8836-7095b4e79e24", "name": "Minnesota Wild @ Colorado Avalanche"}, {"date": "2012-03-09T02:00:00.000000Z", "id": "a7f6b04c-efb6-50dd-985b-7e0b707ee048", "name": "Minnesota Wild @ Phoenix Coyotes"}, {"date": "2012-03-11T22:00:00.000000Z", "id": "84de0feb-da4a-5b2d-ad69-1dc0cfa1c756", "name": "Calgary Flames @ Minnesota Wild"}, {"date": "2012-03-14T00:00:00.000000Z", "id": "b4af875a-328f-5af5-8cc3-b603549e8223", "name": "Dallas Stars @ Minnesota Wild"}, {"date": "2012-03-17T18:00:00.000000Z", "id": "ce79cf66-2b73-5b9b-a083-6f687c422094", "name": "Carolina Hurricanes @ Minnesota Wild"}, {"date": "2012-03-20T00:00:00.000000Z", "id": "ddbe2ec6-13a5-5778-8a4d-53df2f57482d", "name": "Vancouver Canucks @ Minnesota Wild"}, {"date": "2012-03-23T00:00:00.000000Z", "id": "92337389-f639-5632-bef4-992aab55ce29", "name": "Calgary Flames @ Minnesota Wild"}, {"date": "2012-03-24T23:00:00.000000Z", "id": "d537d057-1c3e-56e4-b2ba-f14d87f87ac0", "name": "Minnesota Wild @ Buffalo Sabres"}, {"date": "2012-03-25T21:00:00.000000Z", "id": "cef0fb98-1157-5063-8307-50c8843c2ad8", "name": "Minnesota Wild @ Washington Capitals"}, {"date": "2012-03-28T00:00:00.000000Z", "id": "29fe9725-7226-59d8-ad17-0c30f4e6a2cb", "name": "New York Rangers @ Minnesota Wild"}, {"date": "2012-03-30T00:00:00.000000Z", "id": "31135f2c-60a7-59b6-b348-dac6ea46c6b8", "name": "Florida Panthers @ Minnesota Wild"}, {"date": "2012-04-01T00:00:00.000000Z", "id": "2f6e73d7-cec1-57b9-b9a7-6f7fb393f233", "name": "Los Angeles Kings @ Minnesota Wild"}, {"date": "2012-04-01T23:00:00.000000Z", "id": "592fa0ee-589a-55b2-aae6-ef8bf1288101", "name": "Minnesota Wild @ Chicago Blackhawks"}, {"date": "2012-04-04T00:00:00.000000Z", "id": "fc0dc0a0-50dc-5455-99af-d1f3bba36c12", "name": "Minnesota Wild @ Nashville Predators"}, {"date": "2012-04-06T00:00:00.000000Z", "id": "e98bc76e-2662-5037-ba7e-dcf0ffa58961", "name": "Chicago Blackhawks @ Minnesota Wild"}, {"date": "2012-04-08T00:00:00.000000Z", "id": "e5003e2d-4da6-5e85-9d8f-db99b5491fdc", "name": "Phoenix Coyotes @ Minnesota Wild"}]
